CHANGES.txt
LICENSE.txt
MANIFEST.in
README.rst
setup.cfg
setup.py
django_redirects_file/__init__.py
django_redirects_file/redirects.py
django_redirects_file.egg-info/PKG-INFO
django_redirects_file.egg-info/SOURCES.txt
django_redirects_file.egg-info/dependency_links.txt
django_redirects_file.egg-info/requires.txt
django_redirects_file.egg-info/top_level.txt