Metadata-Version: 1.0
Name: django-redirects-file
Version: 0.1.1
Summary: A simple redirects utility that uses a json file for redirects definitions
Home-page: https://github.com/ubuntudesign/django-redirects-file
Author: Tris
Author-email: tristram.oaten@canonical.com
License: UNKNOWN
Platform: UNKNOWN
